altair_nx/__init__.py
altair_nx/_version.py
altair_nx/_version.pyi
altair_nx/core.py
altair_nx/draw_altair.py
altair_nx/util.py
altair_nx-1.3.dist-info/METADATA
altair_nx-1.3.dist-info/WHEEL
altair_nx-1.3.dist-info/licenses/LICENSE
altair_nx-1.3.dist-info/RECORD
