Metadata-Version: 2.3
Name: altair-nx
Version: 1.3
Summary: Draw interactive NetworkX graphs with Altair
Project-URL: Homepage, https://github.com/T-Flet/altair-nx
Project-URL: Documentation, https://altair-nx.readthedocs.io/en/stable
Project-URL: Bug Tracker, https://github.com/T-Flet/altair-nx/issues
Project-URL: Discussions, https://github.com/T-Flet/altair-nx/discussions
Project-URL: Changelog, https://github.com/T-Flet/altair-nx/releases
Author-email: Thomas Fletcher <T-Fletcher@outlook.com>, Zach Sailer <zachsailer@gmail.com>
License: Copyright (c) for portions of project altair-nx are held by Zach Sailer (2019) as part of project nx-altair.
License-File: LICENSE
Classifier: Development Status :: 5 - Production/Stable
Classifier: Intended Audience :: Developers
Classifier: Intended Audience :: Science/Research
Classifier: License :: OSI Approved :: MIT License
Classifier: Operating System :: OS Independent
Classifier: Programming Language :: Python
Classifier: Programming Language :: Python :: 3
Classifier: Programming Language :: Python :: 3 :: Only
Classifier: Programming Language :: Python :: 3.10
Classifier: Programming Language :: Python :: 3.11
Classifier: Programming Language :: Python :: 3.12
Classifier: Topic :: Scientific/Engineering
Classifier: Typing :: Typed
Requires-Python: >=3.10
Requires-Dist: altair>=5.0.0
Requires-Dist: networkx>=3.0
Requires-Dist: pandas>=2.0.0
Provides-Extra: dev
Requires-Dist: pytest-cov>=3; extra == 'dev'
Requires-Dist: pytest>=6; extra == 'dev'
Provides-Extra: docs
Requires-Dist: furo>=2023.08.17; extra == 'docs'
Requires-Dist: myst-parser>=0.13; extra == 'docs'
Requires-Dist: sphinx-autodoc-typehints; extra == 'docs'
Requires-Dist: sphinx-copybutton; extra == 'docs'
Requires-Dist: sphinx>=7.0; extra == 'docs'
Provides-Extra: test
Requires-Dist: pytest-cov>=3; extra == 'test'
Requires-Dist: pytest>=6; extra == 'test'
